databeak/__init__.py
databeak/_version.py
databeak/exceptions.py
databeak/instructions.md
databeak/py.typed
databeak/server.py
databeak/core/__init__.py
databeak/core/json_schema_validate.py
databeak/core/session.py
databeak/core/settings.py
databeak/models/__init__.py
databeak/models/data_models.py
databeak/models/data_session.py
databeak/models/expression_models.py
databeak/models/statistics_models.py
databeak/models/tool_responses.py
databeak/models/typed_dicts.py
databeak/prompts/__init__.py
databeak/prompts/data_prompts.py
databeak/servers/__init__.py
databeak/servers/column_server.py
databeak/servers/column_text_server.py
databeak/servers/discovery_server.py
databeak/servers/io_server.py
databeak/servers/row_operations_server.py
databeak/servers/statistics_server.py
databeak/servers/system_server.py
databeak/servers/transformation_server.py
databeak/servers/validation_server.py
databeak/services/__init__.py
databeak/services/data_operations.py
databeak/utils/__init__.py
databeak/utils/logging_config.py
databeak/utils/pydantic_validators.py
databeak/utils/secure_evaluator.py
databeak/utils/validators.py
databeak-0.1.2.dist-info/METADATA
databeak-0.1.2.dist-info/WHEEL
databeak-0.1.2.dist-info/entry_points.txt
databeak-0.1.2.dist-info/licenses/LICENSE
databeak-0.1.2.dist-info/licenses/NOTICE
databeak-0.1.2.dist-info/RECORD
