Metadata-Version: 2.4
Name: databeak
Version: 0.1.2
Summary: DataBeak: MCP server for comprehensive CSV file operations with pandas-based tools
Project-URL: Homepage, https://github.com/jonpspri/databeak
Project-URL: Documentation, https://github.com/jonpspri/databeak#readme
Project-URL: Repository, https://github.com/jonpspri/databeak
Project-URL: Issues, https://github.com/jonpspri/databeak/issues
Project-URL: Changelog, https://github.com/jonpspri/databeak/blob/main/CHANGELOG.md
Project-URL: Release Notes, https://github.com/jonpspri/databeak/releases
Author-email: Jonathan Springer <jps@s390x.com>
Maintainer-email: Jonathan Springer <jps@s390x.com>
License: Apache-2.0
License-File: LICENSE
License-File: NOTICE
Keywords: csv,data-analysis,data-manipulation,data-profiling,data-quality,data-validation,fastmcp,mcp,model-context-protocol,outlier-detection,pandas
Classifier: Development Status :: 4 - Beta
Classifier: Framework :: AsyncIO
Classifier: Intended Audience :: Developers
Classifier: Intended Audience :: Financial and Insurance Industry
Classifier: Intended Audience :: Science/Research
Classifier: License :: OSI Approved :: Apache Software License
Classifier: Operating System :: OS Independent
Classifier: Programming Language :: Python
Classifier: Programming Language :: Python :: 3
Classifier: Programming Language :: Python :: 3.12
Classifier: Programming Language :: Python :: 3.13
Classifier: Topic :: Office/Business :: Financial :: Spreadsheet
Classifier: Topic :: Scientific/Engineering :: Information Analysis
Classifier: Topic :: Software Development :: Libraries :: Python Modules
Classifier: Topic :: Utilities
Classifier: Typing :: Typed
Requires-Python: >=3.12
Requires-Dist: aiofiles>=24.1.0
Requires-Dist: chardet>=5.2.0
Requires-Dist: fastapi>=0.117.1
Requires-Dist: fastmcp>=2.12.4
Requires-Dist: httpx>=0.27.0
Requires-Dist: numpy>=2.1.3
Requires-Dist: openpyxl>=3.1.5
Requires-Dist: pandas>=2.2.3
Requires-Dist: pandera>=0.26.1
Requires-Dist: psutil>=7.0.0
Requires-Dist: pyarrow>=17.0.0
Requires-Dist: pydantic-settings>=2.10.1
Requires-Dist: pydantic>=2.10.4
Requires-Dist: python-dateutil>=2.9.0
Requires-Dist: pytz>=2024.2
Requires-Dist: scipy>=1.16.1
Requires-Dist: simpleeval>=1.0.3
Requires-Dist: tabulate>=0.9.0
Requires-Dist: uvicorn>=0.36.0
